rts/__init__.py
rts-0.0.1.dist-info/DESCRIPTION.rst
rts-0.0.1.dist-info/METADATA
rts-0.0.1.dist-info/RECORD
rts-0.0.1.dist-info/WHEEL
rts-0.0.1.dist-info/entry_points.txt
rts-0.0.1.dist-info/metadata.json
rts-0.0.1.dist-info/top_level.txt
sample/__init__.py
sample/package_data.py
