Metadata-Version: 2.0
Name: rts
Version: 0.0.1
Summary: Real-time Task Simulator
Home-page: http://github.com/upoque/Real-timeTaskSimulator
Author: Youngeun Cho
Author-email: upoque@gmail.com
License: MIT
Keywords: real-time simulator schedulability test
Platform: UNKNOWN
Classifier: Development Status :: 3 - Alpha
Classifier: Intended Audience :: Developers
Classifier: Topic :: Software Development :: Testing
Classifier: License :: OSI Approved :: MIT License
Classifier: Programming Language :: Python :: 2.7
Requires-Dist: numpy
Provides-Extra: dev
Requires-Dist: check-manifest; extra == 'dev'
Provides-Extra: test
Requires-Dist: coverage; extra == 'test'
